sn_api_helper_mcp/__init__.py
sn_api_helper_mcp/__main__.py
sn_api_helper_mcp/_version.py
sn_api_helper_mcp/cli.py
sn_api_helper_mcp/server.py
sn_api_helper_mcp/tools/__init__.py
sn_api_helper_mcp/tools/get_skills_info.py
sn_api_helper_mcp-0.1.1.dist-info/METADATA
sn_api_helper_mcp-0.1.1.dist-info/WHEEL
sn_api_helper_mcp-0.1.1.dist-info/entry_points.txt
sn_api_helper_mcp-0.1.1.dist-info/licenses/LICENSE.md
sn_api_helper_mcp-0.1.1.dist-info/RECORD
