Metadata-Version: 2.4
Name: sn-api-helper-mcp
Version: 0.1.1
Summary: MCP server for SignNow API helper tools (stdio only).
Author: SignNow
License: MIT
License-File: LICENSE.md
Requires-Python: >=3.10
Requires-Dist: fastmcp>=2.14.1
Requires-Dist: httpx>=0.27.0
Requires-Dist: pydantic>=2.0.0
Requires-Dist: typer>=0.9.0
